CtrlRound/CtrlRound.py
CtrlRound/__init__.py
CtrlRound/best_first_search.py
CtrlRound/distance.py
CtrlRound/generate_table.py
CtrlRound-0.5.0.dist-info/LICENSE
CtrlRound-0.5.0.dist-info/METADATA
CtrlRound-0.5.0.dist-info/WHEEL
CtrlRound-0.5.0.dist-info/top_level.txt
CtrlRound-0.5.0.dist-info/RECORD
