Metadata-Version: 2.1
Name: CtrlRound
Version: 0.5.0
Summary: Performs controlled rounding of tabular data
Home-page: https://github.com/Veozen/CtrlRound
Author: Christian Gagné
Author-email: christian.gagne@gmail.com
Classifier: Programming Language :: Python :: 3
Classifier: License :: OSI Approved :: MIT License
Classifier: Operating System :: OS Independent
Requires-Python: >=3.10
License-File: LICENSE
Requires-Dist: numpy>=1.23.5
Requires-Dist: pandas>=2.1.2
